README.rst
setup.cfg
setup.py
ckan_api_client/__init__.py
ckan_api_client/cli.py
ckan_api_client/exceptions.py
ckan_api_client/high_level.py
ckan_api_client/low_level.py
ckan_api_client/schema.py
ckan_api_client/syncing.py
ckan_api_client/utils.py
ckan_api_client.egg-info/PKG-INFO
ckan_api_client.egg-info/SOURCES.txt
ckan_api_client.egg-info/dependency_links.txt
ckan_api_client.egg-info/entry_points.txt
ckan_api_client.egg-info/requires.txt
ckan_api_client.egg-info/top_level.txt
ckan_api_client/commands/__init__.py
ckan_api_client/commands/base.py
ckan_api_client/commands/client_hilev.py
ckan_api_client/commands/syncing.py
ckan_api_client/objects/__init__.py
ckan_api_client/objects/base.py
ckan_api_client/objects/ckan_dataset.py
ckan_api_client/objects/ckan_group.py
ckan_api_client/objects/ckan_organization.py
ckan_api_client/objects/fields.py
ckan_api_client/tests/__init__.py
ckan_api_client/tests/conftest.py
ckan_api_client/tests/test_00_startup_and_fixtures.py
ckan_api_client/tests/functional/__init__.py
ckan_api_client/tests/functional/ckan_api/__init__.py
ckan_api_client/tests/functional/ckan_api/test_00_api_readonly.py
ckan_api_client/tests/functional/ckan_api/test_01_simple_crud.py
ckan_api_client/tests/functional/ckan_api/utils.py
ckan_api_client/tests/functional/client_hilev/__init__.py
ckan_api_client/tests/functional/client_hilev/test_dataset_crud.py
ckan_api_client/tests/functional/client_hilev/test_group_crud.py
ckan_api_client/tests/functional/client_hilev/test_organization_crud.py
ckan_api_client/tests/functional/client_lowlev/__init__.py
ckan_api_client/tests/functional/client_lowlev/test_data_loss_on_update.py
ckan_api_client/tests/functional/client_lowlev/test_dataset_crud.py
ckan_api_client/tests/functional/client_lowlev/test_group_crud.py
ckan_api_client/tests/functional/client_lowlev/utils/__init__.py
ckan_api_client/tests/functional/client_lowlev/utils/harvest_source.py
ckan_api_client/tests/functional/client_sync/__init__.py
ckan_api_client/tests/functional/client_sync/test_merging_strategies.py
ckan_api_client/tests/functional/client_sync/test_real_harvesting_scenario.py
ckan_api_client/tests/functional/client_sync/test_simple_harvesting_scenario.py
