Metadata-Version: 1.1
Name: ckan-api-client
Version: 0.1-beta1
Summary: Client for the Ckan API
Home-page: http://rshk.github.io/ckan-api-client
Author: Samuele Santi
Author-email: s.santi@trentorise.eu
License: BSD License
Platform: UNKNOWN
Classifier: License :: OSI Approved :: BSD License
Classifier: Development Status :: 4 - Beta
Classifier: Programming Language :: Python :: 2.6
Classifier: Programming Language :: Python :: 2.7
Classifier: Intended Audience :: Developers
